ttyclock/__init__.py
ttyclock/__main__.py
ttyclock/clock.py
ttyclock/config.py
ttyclock/digits.py
ttyclock/fonts.py
ttyclock/renderer.py
ttyclock/screensaver.py
ttyclock/time_formatter.py
ttyclock/types.py
ttyclock_py-2.0.0.dist-info/METADATA
ttyclock_py-2.0.0.dist-info/WHEEL
ttyclock_py-2.0.0.dist-info/entry_points.txt
ttyclock_py-2.0.0.dist-info/licenses/LICENSE
ttyclock_py-2.0.0.dist-info/RECORD
