Metadata-Version: 2.4
Name: ttyclock-py
Version: 2.0.0
Summary: Basically tty-clock but rewritten in Python
Project-URL: Homepage, https://github.com/elliottophellia/clock.py
Project-URL: Repository, https://github.com/elliottophellia/clock.py
Project-URL: Issues, https://github.com/elliottophellia/clock.py/issues
Author-email: Reidho Satria <me@rei.my.id>
License: CC-BY-SA-4.0
License-File: LICENSE
Classifier: Development Status :: 5 - Production/Stable
Classifier: Environment :: Console
Classifier: Intended Audience :: End Users/Desktop
Classifier: License :: Other/Proprietary License
Classifier: Operating System :: OS Independent
Classifier: Programming Language :: Python :: 3
Classifier: Programming Language :: Python :: 3.10
Classifier: Programming Language :: Python :: 3.11
Classifier: Programming Language :: Python :: 3.12
Classifier: Topic :: Utilities
Requires-Python: >=3.10
Requires-Dist: windows-curses>=2.3.1; sys_platform == 'win32'
